{
  "type": "panel",
  "name": "SP Eventdrops",
  "id": "sp-eventdrops",

  "info": {
    "description": "SP D3 Eventdrops Panel for Grafana.",
    "author": {
      "name": "Segmentproxy",
      "url": "https://github.com/segmentproxy"
    },
    "keywords": ["d3", "panel"],
    "logos": {
      "small": "img/logo.svg",
      "large": "img/logo.svg"
    },
    "links": [
      {"name": "Project site", "url": "https://github.com/segmentproxy/sp-eventdrops"},
      {"name": "MIT License", "url": "https://github.com/segmentproxy/sp-eventdrops"}
    ],
    "screenshots": [
      {"name": "Showcase", "path": "img/screenshot-radar-showcase.jpg"}
    ],
    "version": "1.0.0",
    "updated": "2018-11-23"
  },
  "dependencies": {
    "grafanaVersion": "5.x.x",
    "plugins": [ ]
  }
}
